{
  "id": "mewtwo",
  "dexnum": 150,
  "name": "Mewtwo",
  "primaryType": "psychic",
  "secondaryType": "",
  "maleRatio": -1,
  "labels": [
    "gen1",
    "legendary",
    "restricted"
  ],
  "abilities": [
    "pressure",
    "h:unnerve"
  ],
  "eggGroups": [
    "undiscovered"
  ],
  "baseStats": {
    "hp": 106,
    "attack": 110,
    "defence": 90,
    "special_attack": 154,
    "special_defence": 90,
    "speed": 130
  },
  "evYield": {
    "hp": 0,
    "attack": 0,
    "defence": 0,
    "special_attack": 3,
    "special_defence": 0,
    "speed": 0
  },
  "experienceGroup": "slow",
  "catchRate": 3,
  "drops": {
    "amount": 1,
    "entries": [
      {
        "item": "cobblemon:twisted_spoon",
        "percentage": null,
        "quantityRange": null,
        "source": "species"
      }
    ]
  },
  "moves": [
    "1:confusion",
    "1:disable",
    "1:barrier",
    "1:swift",
    "1:miracleeye",
    "1:mefirst",
    "1:laserfocus",
    "1:psywave",
    "1:lifedew",
    "8:ancientpower",
    "16:psychocut",
    "24:safeguard",
    "32:amnesia",
    "40:aurasphere",
    "48:psychic",
    "56:powerswap",
    "56:guardswap",
    "64:mist",
    "72:psystrike",
    "80:recover",
    "88:futuresight",
    "tm:agility",
    "tm:allyswitch",
    "tm:amnesia",
    "tm:ancientpower",
    "tm:aquatail",
    "tm:aurasphere",
    "tm:avalanche",
    "tm:blizzard",
    "tm:bodyslam",
    "tm:brickbreak",
    "tm:brutalswing",
    "tm:bulkup",
    "tm:bulldoze",
    "tm:calmmind",
    "tm:chillingwater",
    "tm:confuseray",
    "tm:curse",
    "tm:darkpulse",
    "tm:dive",
    "tm:doubleedge",
    "tm:drainpunch",
    "tm:dreameater",
    "tm:earthpower",
    "tm:earthquake",
    "tm:electroball",
    "tm:embargo",
    "tm:endure",
    "tm:energyball",
    "tm:expandingforce",
    "tm:facade",
    "tm:fireblast",
    "tm:firepunch",
    "tm:flamethrower",
    "tm:flash",
    "tm:fling",
    "tm:focusblast",
    "tm:focuspunch",
    "tm:foulplay",
    "tm:futuresight",
    "tm:gigaimpact",
    "tm:grassknot",
    "tm:gravity",
    "tm:guardswap",
    "tm:hail",
    "tm:headbutt",
    "tm:helpinghand",
    "tm:hex",
    "tm:hurricane",
    "tm:hyperbeam",
    "tm:icebeam",
    "tm:icepunch",
    "tm:icywind",
    "tm:imprison",
    "tm:incinerate",
    "tm:irontail",
    "tm:knockoff",
    "tm:laserfocus",
    "tm:lashout",
    "tm:lightscreen",
    "tm:lowkick",
    "tm:lowsweep",
    "tm:magiccoat",
    "tm:magicroom",
    "tm:megakick",
    "tm:megapunch",
    "tm:metronome",
    "tm:nastyplot",
    "tm:nightshade",
    "tm:payday",
    "tm:poisonjab",
    "tm:powergem",
    "tm:powerswap",
    "tm:poweruppunch",
    "tm:protect",
    "tm:psybeam",
    "tm:psychic",
    "tm:psychicnoise",
    "tm:psychicterrain",
    "tm:psychocut",
    "tm:psychup",
    "tm:psyshock",
    "tm:raindance",
    "tm:recycle",
    "tm:reflect",
    "tm:rest",
    "tm:reversal",
    "tm:rockclimb",
    "tm:rockslide",
    "tm:rocksmash",
    "tm:rocktomb",
    "tm:roleplay",
    "tm:safeguard",
    "tm:sandstorm",
    "tm:scaryface",
    "tm:selfdestruct",
    "tm:shadowball",
    "tm:shockwave",
    "tm:signalbeam",
    "tm:skillswap",
    "tm:sleeptalk",
    "tm:snatch",
    "tm:solarbeam",
    "tm:speedswap",
    "tm:spite",
    "tm:stompingtantrum",
    "tm:stoneedge",
    "tm:storedpower",
    "tm:strength",
    "tm:substitute",
    "tm:sunnyday",
    "tm:swift",
    "tm:takedown",
    "tm:taunt",
    "tm:telekinesis",
    "tm:terablast",
    "tm:thunder",
    "tm:thunderbolt",
    "tm:thunderpunch",
    "tm:thunderwave",
    "tm:torment",
    "tm:trailblaze",
    "tm:triattack",
    "tm:trick",
    "tm:trickroom",
    "tm:weatherball",
    "tm:willowisp",
    "tm:wonderroom",
    "tm:zenheadbutt",
    "tutor:allyswitch",
    "tutor:ancientpower",
    "tutor:aquatail",
    "tutor:bulkup",
    "tutor:bulldoze",
    "tutor:calmmind",
    "tutor:darkpulse",
    "tutor:dive",
    "tutor:drainpunch",
    "tutor:earthpower",
    "tutor:energyball",
    "tutor:expandingforce",
    "tutor:firepunch",
    "tutor:flamethrower",
    "tutor:focuspunch",
    "tutor:foulplay",
    "tutor:gigaimpact",
    "tutor:gravity",
    "tutor:helpinghand",
    "tutor:hyperbeam",
    "tutor:icebeam",
    "tutor:icepunch",
    "tutor:icywind",
    "tutor:irontail",
    "tutor:knockoff",
    "tutor:laserfocus",
    "tutor:lashout",
    "tutor:lowkick",
    "tutor:magiccoat",
    "tutor:magicroom",
    "tutor:poisonjab",
    "tutor:psychic",
    "tutor:psychocut",
    "tutor:recycle",
    "tutor:rest",
    "tutor:rockslide",
    "tutor:rocksmash",
    "tutor:roleplay",
    "tutor:shadowball",
    "tutor:shockwave",
    "tutor:signalbeam",
    "tutor:skillswap",
    "tutor:sleeptalk",
    "tutor:snatch",
    "tutor:spite",
    "tutor:stompingtantrum",
    "tutor:stoneedge",
    "tutor:swift",
    "tutor:telekinesis",
    "tutor:thunderbolt",
    "tutor:thunderpunch",
    "tutor:trick",
    "tutor:wonderroom",
    "tutor:zenheadbutt",
    "legacy:aerialace",
    "legacy:bide",
    "legacy:bubblebeam",
    "legacy:chargebeam",
    "legacy:confide",
    "legacy:counter",
    "legacy:detect",
    "legacy:doubleteam",
    "legacy:dynamicpunch",
    "legacy:frustration",
    "legacy:hiddenpower",
    "legacy:mimic",
    "legacy:mudslap",
    "legacy:naturalgift",
    "legacy:nightmare",
    "legacy:rage",
    "legacy:return",
    "legacy:round",
    "legacy:secretpower",
    "legacy:seismictoss",
    "legacy:skullbash",
    "legacy:snore",
    "legacy:submission",
    "legacy:swagger",
    "legacy:teleport",
    "legacy:toxic",
    "legacy:watergun",
    "legacy:waterpulse",
    "legacy:zapcannon",
    "special:healpulse"
  ],
  "forms": [
    "Mega-X",
    "Mega-Y"
  ],
  "types": [],
  "evolutions": [],
  "spawns": [],
  "implemented": true,
  "images": {
    "normal": [
      "out/sprites/genomons/mewtwo.png",
      "out/sprites/cobblemon/mewtwo.png"
    ],
    "shiny": [
      "out/sprites/genomons/mewtwo_shiny.png",
      "out/sprites/cobblemon/mewtwo_shiny.png"
    ]
  },
  "speciesSources": [
    "Abes-Hutts-Cobblemon-1.21.1.1.7.3-1.0.2.jar!/data/cobblemon/species/generation1/mewtwo.json"
  ]
}